igvf_utils/__init__.py
igvf_utils/aws_storage.py
igvf_utils/connection.py
igvf_utils/exceptions.py
igvf_utils/gc_storage.py
igvf_utils/parent_argparser.py
igvf_utils/profiles.py
igvf_utils/replicate.py
igvf_utils/transfer_to_gcp.py
igvf_utils/utils.py
igvf_utils/version.py
igvf_utils/MetaDataRegistration/__init__.py
igvf_utils/MetaDataRegistration/iu_register.py
igvf_utils/scripts/__init__.py
igvf_utils/scripts/iu_check_not_posted.py
igvf_utils/scripts/iu_create_gcp_url_list.py
igvf_utils/scripts/iu_generate_upload_creds.py
igvf_utils/scripts/iu_get_accessions.py
igvf_utils/scripts/iu_get_aliases.py
igvf_utils/scripts/iu_patch_property.py
igvf_utils/scripts/iu_s3_to_gcp.py
igvf_utils/scripts/iu_search_results_json.py
igvf_utils/tests/data/estarr_counts.as
igvf_utils/tests/data/replicates_for_IGVFSR502NRF.json
igvf_utils/tests/data/register/patch_biosamples.tsv
igvf_utils-3.1.1.dist-info/licenses/LICENSE.txt
igvf_utils-3.1.1.dist-info/METADATA
igvf_utils-3.1.1.dist-info/WHEEL
igvf_utils-3.1.1.dist-info/entry_points.txt
igvf_utils-3.1.1.dist-info/top_level.txt
igvf_utils-3.1.1.dist-info/RECORD
