Metadata-Version: 2.4
Name: igvf-utils
Version: 3.1.1
Summary: Client and tools for IGVF data submitters.
Author-email: Jennifer Jou <jjou@stanford.edu>
Maintainer-email: Otto Jolanki <ojolanki@stanford.edu>, Jennifer Jou <jjou@stanford.edu>
License-Expression: MIT
Project-URL: Homepage, https://github.com/IGVF-DACC/igvf_utils
Project-URL: Documentation, http://igvf-utils.readthedocs.io/
Project-URL: Repository, https://github.com/IGVF-DACC/igvf_utils
Project-URL: Issues, https://github.com/IGVF-DACC/igvf_utils/issues
Keywords: genomics,IGVF,data-submission,bioinformatics
Classifier: Development Status :: 5 - Production/Stable
Classifier: Intended Audience :: Science/Research
Classifier: Operating System :: OS Independent
Classifier: Programming Language :: Python :: 3
Classifier: Programming Language :: Python :: 3.8
Classifier: Programming Language :: Python :: 3.9
Classifier: Programming Language :: Python :: 3.10
Classifier: Programming Language :: Python :: 3.11
Classifier: Programming Language :: Python :: 3.12
Classifier: Topic :: Scientific/Engineering :: Bio-Informatics
Requires-Python: >=3.8
License-File: LICENSE.txt
Requires-Dist: awscli
Requires-Dist: boto3
Requires-Dist: exifread
Requires-Dist: google-api-python-client
Requires-Dist: google-cloud-storage
Requires-Dist: inflection
Requires-Dist: jsonschema
Requires-Dist: packaging
Requires-Dist: pillow
Requires-Dist: requests
Requires-Dist: urllib3
Provides-Extra: docs
Requires-Dist: sphinx; extra == "docs"
Requires-Dist: sphinx-rtd-theme; extra == "docs"
Dynamic: license-file
